[
    {
        "company_name": "7500 INR (Approx.)",
        "website": "https://www.tradeindia.com/products/mild-steel-ms-street-light-octagonal-pole-c10487742.html",
        "country": "India",
        "industries_served": [
            "General Manufacturing"
        ],
        "manufacturing_processes": [
            "Unknown"
        ],
        "certifications": [
            "Unknown"
        ],
        "customers": [
            "Unknown"
        ],
        "employees": "Unknown",
        "annual_revenue": "Unknown",
        "score": 1
    },
    {
        "company_name": "1250 INR (Approx.)",
        "website": "https://www.tradeindia.com/products/ss-tube-fittings-c640063.html",
        "country": "India",
        "industries_served": [
            "General Manufacturing"
        ],
        "manufacturing_processes": [
            "Unknown"
        ],
        "certifications": [
            "Unknown"
        ],
        "customers": [
            "Unknown"
        ],
        "employees": "Unknown",
        "annual_revenue": "Unknown",
        "score": 1
    },
    {
        "company_name": "25000.00 INR (Approx.)",
        "website": "https://www.tradeindia.com/products/ms-conveyor-roller-c5550949.html",
        "country": "India",
        "industries_served": [
            "General Manufacturing"
        ],
        "manufacturing_processes": [
            "Unknown"
        ],
        "certifications": [
            "Unknown"
        ],
        "customers": [
            "Unknown"
        ],
        "employees": "Unknown",
        "annual_revenue": "Unknown",
        "score": 1
    },
    {
        "company_name": "270 INR (Approx.)",
        "website": "https://www.tradeindia.com/products/corrugated-roofing-sheets-c2548057.html",
        "country": "India",
        "industries_served": [
            "General Manufacturing"
        ],
        "manufacturing_processes": [
            "Unknown"
        ],
        "certifications": [
            "Unknown"
        ],
        "customers": [
            "Unknown"
        ],
        "employees": "Unknown",
        "annual_revenue": "Unknown",
        "score": 1
    },
    {
        "company_name": "220 INR (Approx.)",
        "website": "https://www.tradeindia.com/products/calcium-nitrite-corrosion-inhibitor-for-steel-bar-road-construction-c8488167.html",
        "country": "India",
        "industries_served": [
            "General Manufacturing"
        ],
        "manufacturing_processes": [
            "Unknown"
        ],
        "certifications": [
            "Unknown"
        ],
        "customers": [
            "Unknown"
        ],
        "employees": "Unknown",
        "annual_revenue": "Unknown",
        "score": 1
    },
    {
        "company_name": "93220.00 INR (Approx.)",
        "website": "https://www.tradeindia.com/products/industrial-steel-dehumidifier-c6407727.html",
        "country": "India",
        "industries_served": [
            "General Manufacturing"
        ],
        "manufacturing_processes": [
            "Unknown"
        ],
        "certifications": [
            "Unknown"
        ],
        "customers": [
            "Unknown"
        ],
        "employees": "Unknown",
        "annual_revenue": "Unknown",
        "score": 1
    },
    {
        "company_name": "100000 INR (Approx.)",
        "website": "https://www.tradeindia.com/products/innovative-pharmaceutical-stainless-steel-furniture-c9285974.html",
        "country": "India",
        "industries_served": [
            "General Manufacturing"
        ],
        "manufacturing_processes": [
            "Unknown"
        ],
        "certifications": [
            "Unknown"
        ],
        "customers": [
            "Unknown"
        ],
        "employees": "Unknown",
        "annual_revenue": "Unknown",
        "score": 1
    },
    {
        "company_name": "TARGET INNOVATIONS",
        "website": "https://www.tradeindia.com/products/gravity-feed-metal-detector-5839502.html",
        "country": "India",
        "industries_served": [
            "General Manufacturing"
        ],
        "manufacturing_processes": [
            "Unknown"
        ],
        "certifications": [
            "Unknown"
        ],
        "customers": [
            "Unknown"
        ],
        "employees": "Unknown",
        "annual_revenue": "Unknown",
        "score": 1
    },
    {
        "company_name": "75000.00 - 100000.00 INR (Approx.)",
        "website": "https://www.tradeindia.com/products/htgs-earth-wire-c5465734.html",
        "country": "India",
        "industries_served": [
            "General Manufacturing"
        ],
        "manufacturing_processes": [
            "Unknown"
        ],
        "certifications": [
            "Unknown"
        ],
        "customers": [
            "Unknown"
        ],
        "employees": "Unknown",
        "annual_revenue": "Unknown",
        "score": 1
    },
    {
        "company_name": "25 INR (Approx.)",
        "website": "https://www.tradeindia.com/products/stainless-steel-forcep-c7288589.html",
        "country": "India",
        "industries_served": [
            "General Manufacturing"
        ],
        "manufacturing_processes": [
            "Unknown"
        ],
        "certifications": [
            "Unknown"
        ],
        "customers": [
            "Unknown"
        ],
        "employees": "Unknown",
        "annual_revenue": "Unknown",
        "score": 1
    },
    {
        "company_name": "585000.0 INR (Approx.)",
        "website": "https://www.tradeindia.com/products/stainless-steel-pressure-vessel-c5649647.html",
        "country": "India",
        "industries_served": [
            "General Manufacturing"
        ],
        "manufacturing_processes": [
            "Unknown"
        ],
        "certifications": [
            "Unknown"
        ],
        "customers": [
            "Unknown"
        ],
        "employees": "Unknown",
        "annual_revenue": "Unknown",
        "score": 1
    },
    {
        "company_name": "K V METACHEM",
        "website": "https://www.tradeindia.com/products/rice-husk-ash-for-steel-productions-7594885.html",
        "country": "India",
        "industries_served": [
            "General Manufacturing"
        ],
        "manufacturing_processes": [
            "Unknown"
        ],
        "certifications": [
            "Unknown"
        ],
        "customers": [
            "Unknown"
        ],
        "employees": "Unknown",
        "annual_revenue": "Unknown",
        "score": 1
    },
    {
        "company_name": "15 INR (Approx.)",
        "website": "https://www.tradeindia.com/products/stainless-steel-speed-nut-c2524419.html",
        "country": "India",
        "industries_served": [
            "General Manufacturing"
        ],
        "manufacturing_processes": [
            "Unknown"
        ],
        "certifications": [
            "Unknown"
        ],
        "customers": [
            "Unknown"
        ],
        "employees": "Unknown",
        "annual_revenue": "Unknown",
        "score": 1
    },
    {
        "company_name": "70 INR (Approx.)",
        "website": "https://www.tradeindia.com/products/stainless-steel-gloves-c4845671.html",
        "country": "India",
        "industries_served": [
            "General Manufacturing"
        ],
        "manufacturing_processes": [
            "Unknown"
        ],
        "certifications": [
            "Unknown"
        ],
        "customers": [
            "Unknown"
        ],
        "employees": "Unknown",
        "annual_revenue": "Unknown",
        "score": 1
    },
    {
        "company_name": "2500 INR (Approx.)",
        "website": "https://www.tradeindia.com/products/conveyor-pulleys-c6440918.html",
        "country": "India",
        "industries_served": [
            "General Manufacturing"
        ],
        "manufacturing_processes": [
            "Unknown"
        ],
        "certifications": [
            "Unknown"
        ],
        "customers": [
            "Unknown"
        ],
        "employees": "Unknown",
        "annual_revenue": "Unknown",
        "score": 1
    },
    {
        "company_name": "MOQ - 10 Unit/Units",
        "website": "https://www.tradeindia.com/products/ptfe-lined-basket-strainer-c6342417.html",
        "country": "India",
        "industries_served": [
            "General Manufacturing"
        ],
        "manufacturing_processes": [
            "Unknown"
        ],
        "certifications": [
            "Unknown"
        ],
        "customers": [
            "Unknown"
        ],
        "employees": "Unknown",
        "annual_revenue": "Unknown",
        "score": 1
    },
    {
        "company_name": "160.00 - 190.00 INR (Approx.)",
        "website": "https://www.tradeindia.com/products/full-threaded-rods-c4366005.html",
        "country": "India",
        "industries_served": [
            "General Manufacturing"
        ],
        "manufacturing_processes": [
            "Unknown"
        ],
        "certifications": [
            "Unknown"
        ],
        "customers": [
            "Unknown"
        ],
        "employees": "Unknown",
        "annual_revenue": "Unknown",
        "score": 1
    },
    {
        "company_name": "20 INR (Approx.)",
        "website": "https://www.tradeindia.com/products/ms-square-insert-c2746690.html",
        "country": "India",
        "industries_served": [
            "General Manufacturing"
        ],
        "manufacturing_processes": [
            "Unknown"
        ],
        "certifications": [
            "Unknown"
        ],
        "customers": [
            "Unknown"
        ],
        "employees": "Unknown",
        "annual_revenue": "Unknown",
        "score": 1
    },
    {
        "company_name": "10500 INR (Approx.)",
        "website": "https://www.tradeindia.com/products/stainless-steel-butterfly-valve-c7245569.html",
        "country": "India",
        "industries_served": [
            "General Manufacturing"
        ],
        "manufacturing_processes": [
            "Unknown"
        ],
        "certifications": [
            "Unknown"
        ],
        "customers": [
            "Unknown"
        ],
        "employees": "Unknown",
        "annual_revenue": "Unknown",
        "score": 1
    },
    {
        "company_name": "575.50 - 615.00 INR (Approx.)",
        "website": "https://www.tradeindia.com/products/steel-v-cross-arm-c2155238.html",
        "country": "India",
        "industries_served": [
            "General Manufacturing"
        ],
        "manufacturing_processes": [
            "Unknown"
        ],
        "certifications": [
            "Unknown"
        ],
        "customers": [
            "Unknown"
        ],
        "employees": "Unknown",
        "annual_revenue": "Unknown",
        "score": 1
    },
    {
        "company_name": "135000 INR (Approx.)",
        "website": "https://www.tradeindia.com/products/mild-steel-automatic-palletizer-6478793.html",
        "country": "India",
        "industries_served": [
            "General Manufacturing"
        ],
        "manufacturing_processes": [
            "Unknown"
        ],
        "certifications": [
            "Unknown"
        ],
        "customers": [
            "Unknown"
        ],
        "employees": "Unknown",
        "annual_revenue": "Unknown",
        "score": 1
    },
    {
        "company_name": "100000.00 INR (Approx.)",
        "website": "https://www.tradeindia.com/products/stainless-steel-mixing-tank-c2365965.html",
        "country": "India",
        "industries_served": [
            "General Manufacturing"
        ],
        "manufacturing_processes": [
            "Unknown"
        ],
        "certifications": [
            "Unknown"
        ],
        "customers": [
            "Unknown"
        ],
        "employees": "Unknown",
        "annual_revenue": "Unknown",
        "score": 1
    },
    {
        "company_name": "2300000 INR (Approx.)",
        "website": "https://www.tradeindia.com/products/mild-steel-coal-crusher-c6227989.html",
        "country": "India",
        "industries_served": [
            "General Manufacturing"
        ],
        "manufacturing_processes": [
            "Unknown"
        ],
        "certifications": [
            "Unknown"
        ],
        "customers": [
            "Unknown"
        ],
        "employees": "Unknown",
        "annual_revenue": "Unknown",
        "score": 1
    },
    {
        "company_name": "ESSAE TERAOKA PRIVATE LIMITED",
        "website": "https://www.tradeindia.com/products/steel-gps-clock-9080380.html",
        "country": "India",
        "industries_served": [
            "General Manufacturing"
        ],
        "manufacturing_processes": [
            "Unknown"
        ],
        "certifications": [
            "Unknown"
        ],
        "customers": [
            "Unknown"
        ],
        "employees": "Unknown",
        "annual_revenue": "Unknown",
        "score": 1
    },
    {
        "company_name": "1550 INR (Approx.)",
        "website": "https://www.tradeindia.com/products/steel-puf-panel-for-cold-rooms-120mm-to-150mm-c9372004.html",
        "country": "India",
        "industries_served": [
            "General Manufacturing"
        ],
        "manufacturing_processes": [
            "Unknown"
        ],
        "certifications": [
            "Unknown"
        ],
        "customers": [
            "Unknown"
        ],
        "employees": "Unknown",
        "annual_revenue": "Unknown",
        "score": 1
    },
    {
        "company_name": "GOLDEN ENGINEERING CO. PVT. LTD.",
        "website": "https://www.tradeindia.com/products/stainless-steel-ventilator-c2626994.html",
        "country": "India",
        "industries_served": [
            "General Manufacturing"
        ],
        "manufacturing_processes": [
            "Unknown"
        ],
        "certifications": [
            "Unknown"
        ],
        "customers": [
            "Unknown"
        ],
        "employees": "Unknown",
        "annual_revenue": "Unknown",
        "score": 1
    },
    {
        "company_name": "62 INR (Approx.)",
        "website": "https://www.tradeindia.com/products/heavy-steel-prefabricated-structure-c5394691.html",
        "country": "India",
        "industries_served": [
            "General Manufacturing"
        ],
        "manufacturing_processes": [
            "Unknown"
        ],
        "certifications": [
            "Unknown"
        ],
        "customers": [
            "Unknown"
        ],
        "employees": "Unknown",
        "annual_revenue": "Unknown",
        "score": 1
    },
    {
        "company_name": "2700 INR (Approx.)",
        "website": "https://www.tradeindia.com/products/steel-hand-trolley-c8411835.html",
        "country": "India",
        "industries_served": [
            "General Manufacturing"
        ],
        "manufacturing_processes": [
            "Unknown"
        ],
        "certifications": [
            "Unknown"
        ],
        "customers": [
            "Unknown"
        ],
        "employees": "Unknown",
        "annual_revenue": "Unknown",
        "score": 1
    },
    {
        "company_name": "600 INR (Approx.)",
        "website": "https://www.tradeindia.com/products/stainless-steel-algae-removal-brush-c8522612.html",
        "country": "India",
        "industries_served": [
            "General Manufacturing"
        ],
        "manufacturing_processes": [
            "Unknown"
        ],
        "certifications": [
            "Unknown"
        ],
        "customers": [
            "Unknown"
        ],
        "employees": "Unknown",
        "annual_revenue": "Unknown",
        "score": 1
    },
    {
        "company_name": "80000 INR (Approx.)",
        "website": "https://www.tradeindia.com/products/industrial-portable-gantry-crane-c5998182.html",
        "country": "India",
        "industries_served": [
            "General Manufacturing"
        ],
        "manufacturing_processes": [
            "Unknown"
        ],
        "certifications": [
            "Unknown"
        ],
        "customers": [
            "Unknown"
        ],
        "employees": "Unknown",
        "annual_revenue": "Unknown",
        "score": 1
    },
    {
        "company_name": "DHIREN PLASTIC INDUSTRIES",
        "website": "https://www.tradeindia.com/products/stainless-steel-caps-616129.html",
        "country": "India",
        "industries_served": [
            "General Manufacturing"
        ],
        "manufacturing_processes": [
            "Unknown"
        ],
        "certifications": [
            "Unknown"
        ],
        "customers": [
            "Unknown"
        ],
        "employees": "Unknown",
        "annual_revenue": "Unknown",
        "score": 1
    },
    {
        "company_name": "100 INR (Approx.)",
        "website": "https://www.tradeindia.com/products/rust-resistance-paint-coated-mild-steel-connector-for-automotive-use-8391248.html",
        "country": "India",
        "industries_served": [
            "General Manufacturing"
        ],
        "manufacturing_processes": [
            "Unknown"
        ],
        "certifications": [
            "Unknown"
        ],
        "customers": [
            "Unknown"
        ],
        "employees": "Unknown",
        "annual_revenue": "Unknown",
        "score": 1
    },
    {
        "company_name": "45000 INR (Approx.)",
        "website": "https://www.tradeindia.com/products/stainless-steel-gyro-screen-c5758802.html",
        "country": "India",
        "industries_served": [
            "General Manufacturing"
        ],
        "manufacturing_processes": [
            "Unknown"
        ],
        "certifications": [
            "Unknown"
        ],
        "customers": [
            "Unknown"
        ],
        "employees": "Unknown",
        "annual_revenue": "Unknown",
        "score": 1
    },
    {
        "company_name": "1500000 INR (Approx.)",
        "website": "https://www.tradeindia.com/products/glycol-water-cooled-chiller-9039779.html",
        "country": "India",
        "industries_served": [
            "General Manufacturing"
        ],
        "manufacturing_processes": [
            "Unknown"
        ],
        "certifications": [
            "Unknown"
        ],
        "customers": [
            "Unknown"
        ],
        "employees": "Unknown",
        "annual_revenue": "Unknown",
        "score": 1
    },
    {
        "company_name": "200000 INR (Approx.)",
        "website": "https://www.tradeindia.com/products/fm-200-gas-flooding-system-c9012145.html",
        "country": "India",
        "industries_served": [
            "General Manufacturing"
        ],
        "manufacturing_processes": [
            "Unknown"
        ],
        "certifications": [
            "Unknown"
        ],
        "customers": [
            "Unknown"
        ],
        "employees": "Unknown",
        "annual_revenue": "Unknown",
        "score": 1
    },
    {
        "company_name": "1200.0 INR (Approx.)",
        "website": "https://www.tradeindia.com/products/insulated-sandwich-panels-c9452650.html",
        "country": "India",
        "industries_served": [
            "General Manufacturing"
        ],
        "manufacturing_processes": [
            "Unknown"
        ],
        "certifications": [
            "Unknown"
        ],
        "customers": [
            "Unknown"
        ],
        "employees": "Unknown",
        "annual_revenue": "Unknown",
        "score": 1
    },
    {
        "company_name": "100 INR (Approx.)",
        "website": "https://www.tradeindia.com/products/p20-steel-plate-c1956460.html",
        "country": "India",
        "industries_served": [
            "General Manufacturing"
        ],
        "manufacturing_processes": [
            "Unknown"
        ],
        "certifications": [
            "Unknown"
        ],
        "customers": [
            "Unknown"
        ],
        "employees": "Unknown",
        "annual_revenue": "Unknown",
        "score": 1
    },
    {
        "company_name": "1025 USD ($) (Approx.)",
        "website": "https://www.tradeindia.com/products/low-carbon-ferro-silicon-manganese-c8732760.html",
        "country": "India",
        "industries_served": [
            "General Manufacturing"
        ],
        "manufacturing_processes": [
            "Unknown"
        ],
        "certifications": [
            "Unknown"
        ],
        "customers": [
            "Unknown"
        ],
        "employees": "Unknown",
        "annual_revenue": "Unknown",
        "score": 1
    },
    {
        "company_name": "MOQ - 1 Unit/Units",
        "website": "https://www.tradeindia.com/products/industrial-lifts-c5031135.html",
        "country": "India",
        "industries_served": [
            "General Manufacturing"
        ],
        "manufacturing_processes": [
            "Unknown"
        ],
        "certifications": [
            "Unknown"
        ],
        "customers": [
            "Unknown"
        ],
        "employees": "Unknown",
        "annual_revenue": "Unknown",
        "score": 1
    },
    {
        "company_name": "100 INR (Approx.)",
        "website": "https://www.tradeindia.com/products/ss-304l-scrap-c10164971.html",
        "country": "India",
        "industries_served": [
            "General Manufacturing"
        ],
        "manufacturing_processes": [
            "Unknown"
        ],
        "certifications": [
            "Unknown"
        ],
        "customers": [
            "Unknown"
        ],
        "employees": "Unknown",
        "annual_revenue": "Unknown",
        "score": 1
    },
    {
        "company_name": "90000 INR (Approx.)",
        "website": "https://www.tradeindia.com/products/prefabricated-steel-building-c4221017.html",
        "country": "India",
        "industries_served": [
            "General Manufacturing"
        ],
        "manufacturing_processes": [
            "Unknown"
        ],
        "certifications": [
            "Unknown"
        ],
        "customers": [
            "Unknown"
        ],
        "employees": "Unknown",
        "annual_revenue": "Unknown",
        "score": 1
    },
    {
        "company_name": "54.0 INR (Approx.)",
        "website": "https://www.tradeindia.com/products/mild-steel-tube-c8470942.html",
        "country": "India",
        "industries_served": [
            "General Manufacturing"
        ],
        "manufacturing_processes": [
            "Unknown"
        ],
        "certifications": [
            "Unknown"
        ],
        "customers": [
            "Unknown"
        ],
        "employees": "Unknown",
        "annual_revenue": "Unknown",
        "score": 1
    },
    {
        "company_name": "3000.00 INR (Approx.)",
        "website": "https://www.tradeindia.com/products/swaged-type-steel-tubular-poles-c237453.html",
        "country": "India",
        "industries_served": [
            "General Manufacturing"
        ],
        "manufacturing_processes": [
            "Unknown"
        ],
        "certifications": [
            "Unknown"
        ],
        "customers": [
            "Unknown"
        ],
        "employees": "Unknown",
        "annual_revenue": "Unknown",
        "score": 1
    },
    {
        "company_name": "MOQ - 4 Unit/Units",
        "website": "https://www.tradeindia.com/products/stainless-steel-stretcher-trolley-c5463737.html",
        "country": "India",
        "industries_served": [
            "General Manufacturing"
        ],
        "manufacturing_processes": [
            "Unknown"
        ],
        "certifications": [
            "Unknown"
        ],
        "customers": [
            "Unknown"
        ],
        "employees": "Unknown",
        "annual_revenue": "Unknown",
        "score": 1
    },
    {
        "company_name": "A. B. ENTERPRISES",
        "website": "https://www.tradeindia.com/products/orthophosphoric-acid-85-ar-for-steel-industry-c6707881.html",
        "country": "India",
        "industries_served": [
            "General Manufacturing"
        ],
        "manufacturing_processes": [
            "Unknown"
        ],
        "certifications": [
            "Unknown"
        ],
        "customers": [
            "Unknown"
        ],
        "employees": "Unknown",
        "annual_revenue": "Unknown",
        "score": 1
    },
    {
        "company_name": "12000 INR (Approx.)",
        "website": "https://www.tradeindia.com/products/plate-magnet-c3868960.html",
        "country": "India",
        "industries_served": [
            "General Manufacturing"
        ],
        "manufacturing_processes": [
            "Unknown"
        ],
        "certifications": [
            "Unknown"
        ],
        "customers": [
            "Unknown"
        ],
        "employees": "Unknown",
        "annual_revenue": "Unknown",
        "score": 1
    },
    {
        "company_name": "50000.00 - 500000.00 INR (Approx.)",
        "website": "https://www.tradeindia.com/products/trolley-ss-c952380.html",
        "country": "India",
        "industries_served": [
            "General Manufacturing"
        ],
        "manufacturing_processes": [
            "Unknown"
        ],
        "certifications": [
            "Unknown"
        ],
        "customers": [
            "Unknown"
        ],
        "employees": "Unknown",
        "annual_revenue": "Unknown",
        "score": 1
    },
    {
        "company_name": "MOQ - 100 Kilograms/Kilograms",
        "website": "https://www.tradeindia.com/products/steel-tmt-bar-c7149267.html",
        "country": "India",
        "industries_served": [
            "General Manufacturing"
        ],
        "manufacturing_processes": [
            "Unknown"
        ],
        "certifications": [
            "Unknown"
        ],
        "customers": [
            "Unknown"
        ],
        "employees": "Unknown",
        "annual_revenue": "Unknown",
        "score": 1
    },
    {
        "company_name": "120 INR (Approx.)",
        "website": "https://www.tradeindia.com/products/stainless-steel-pharma-ultrasonic-cleaners-c7430619.html",
        "country": "India",
        "industries_served": [
            "General Manufacturing"
        ],
        "manufacturing_processes": [
            "Unknown"
        ],
        "certifications": [
            "Unknown"
        ],
        "customers": [
            "Unknown"
        ],
        "employees": "Unknown",
        "annual_revenue": "Unknown",
        "score": 1
    },
    {
        "company_name": "1000 INR (Approx.)",
        "website": "https://www.tradeindia.com/products/stainless-steel-algae-removal-brush-c4758088.html",
        "country": "India",
        "industries_served": [
            "General Manufacturing"
        ],
        "manufacturing_processes": [
            "Unknown"
        ],
        "certifications": [
            "Unknown"
        ],
        "customers": [
            "Unknown"
        ],
        "employees": "Unknown",
        "annual_revenue": "Unknown",
        "score": 1
    },
    {
        "company_name": "10000.00 - 100000.00 INR (Approx.)",
        "website": "https://www.tradeindia.com/products/stainless-steel-pot-rack-c659595.html",
        "country": "India",
        "industries_served": [
            "General Manufacturing"
        ],
        "manufacturing_processes": [
            "Unknown"
        ],
        "certifications": [
            "Unknown"
        ],
        "customers": [
            "Unknown"
        ],
        "employees": "Unknown",
        "annual_revenue": "Unknown",
        "score": 1
    },
    {
        "company_name": "50-150 INR (Approx.)",
        "website": "https://www.tradeindia.com/products/cutting-wheel-c7093928.html",
        "country": "India",
        "industries_served": [
            "General Manufacturing"
        ],
        "manufacturing_processes": [
            "Unknown"
        ],
        "certifications": [
            "Unknown"
        ],
        "customers": [
            "Unknown"
        ],
        "employees": "Unknown",
        "annual_revenue": "Unknown",
        "score": 1
    },
    {
        "company_name": "800.00 USD ($) (Approx.)",
        "website": "https://www.tradeindia.com/products/grey-cast-iron-manhole-cover-c5368201.html",
        "country": "India",
        "industries_served": [
            "General Manufacturing"
        ],
        "manufacturing_processes": [
            "Unknown"
        ],
        "certifications": [
            "Unknown"
        ],
        "customers": [
            "Unknown"
        ],
        "employees": "Unknown",
        "annual_revenue": "Unknown",
        "score": 1
    },
    {
        "company_name": "5000 INR (Approx.)",
        "website": "https://www.tradeindia.com/products/slotted-angle-shelving-racks-c4636595.html",
        "country": "India",
        "industries_served": [
            "General Manufacturing"
        ],
        "manufacturing_processes": [
            "Unknown"
        ],
        "certifications": [
            "Unknown"
        ],
        "customers": [
            "Unknown"
        ],
        "employees": "Unknown",
        "annual_revenue": "Unknown",
        "score": 1
    },
    {
        "company_name": "155000 INR (Approx.)",
        "website": "https://www.tradeindia.com/products/mild-steel-paper-roll-stacker-c9489170.html",
        "country": "India",
        "industries_served": [
            "General Manufacturing"
        ],
        "manufacturing_processes": [
            "Unknown"
        ],
        "certifications": [
            "Unknown"
        ],
        "customers": [
            "Unknown"
        ],
        "employees": "Unknown",
        "annual_revenue": "Unknown",
        "score": 1
    },
    {
        "company_name": "230 INR (Approx.)",
        "website": "https://www.tradeindia.com/products/duplex-steel-plates-c8637670.html",
        "country": "India",
        "industries_served": [
            "General Manufacturing"
        ],
        "manufacturing_processes": [
            "Unknown"
        ],
        "certifications": [
            "Unknown"
        ],
        "customers": [
            "Unknown"
        ],
        "employees": "Unknown",
        "annual_revenue": "Unknown",
        "score": 1
    },
    {
        "company_name": "ShenZhen City infinity Precision Manufactur CO.LTD",
        "website": "https://www.mfg.comhttps://www.mfg.com/manufacturer/shenzhen-city-infinity-precision-manufactur-coltd-guangdong-1789827",
        "country": "Asia",
        "industries_served": [
            "General Manufacturing"
        ],
        "manufacturing_processes": [
            "Unknown"
        ],
        "certifications": [
            "Unknown"
        ],
        "customers": [
            "Unknown"
        ],
        "employees": "Unknown",
        "annual_revenue": "Unknown",
        "score": 1
    },
    {
        "company_name": "Shenzhen Xmake Technology Co.,Ltd",
        "website": "https://www.mfg.comhttps://www.mfg.com/manufacturer/shenzhen-xmake-technology-coltd-shenzhen-guangdong-1863746",
        "country": "Asia",
        "industries_served": [
            "General Manufacturing"
        ],
        "manufacturing_processes": [
            "Unknown"
        ],
        "certifications": [
            "Unknown"
        ],
        "customers": [
            "Unknown"
        ],
        "employees": "Unknown",
        "annual_revenue": "Unknown",
        "score": 1
    },
    {
        "company_name": "Wuxi Qian He Precision Machinery Co.,Ltd.",
        "website": "https://www.mfg.comhttps://www.mfg.com/manufacturer/wuxi-qian-he-precision-machinery-coltd-wuxi-jiangsu-667045",
        "country": "Asia",
        "industries_served": [
            "General Manufacturing"
        ],
        "manufacturing_processes": [
            "Unknown"
        ],
        "certifications": [
            "Unknown"
        ],
        "customers": [
            "Unknown"
        ],
        "employees": "Unknown",
        "annual_revenue": "Unknown",
        "score": 1
    },
    {
        "company_name": "Success Precision Engineering Co., Limited.",
        "website": "https://www.mfg.comhttps://www.mfg.com/manufacturer/success-precision-engineering-co-limited-dongguan-guangdong-1172999",
        "country": "Asia",
        "industries_served": [
            "General Manufacturing"
        ],
        "manufacturing_processes": [
            "Unknown"
        ],
        "certifications": [
            "Unknown"
        ],
        "customers": [
            "Unknown"
        ],
        "employees": "Unknown",
        "annual_revenue": "Unknown",
        "score": 1
    },
    {
        "company_name": "Maysea Ltd",
        "website": "https://www.mfg.comhttps://www.mfg.com/manufacturer/maysea-ltd-shanghai-1152377",
        "country": "Asia",
        "industries_served": [
            "General Manufacturing"
        ],
        "manufacturing_processes": [
            "Unknown"
        ],
        "certifications": [
            "Unknown"
        ],
        "customers": [
            "Unknown"
        ],
        "employees": "Unknown",
        "annual_revenue": "Unknown",
        "score": 1
    },
    {
        "company_name": "Anxin Metal & Plastic Products (HK) Co ., Limited",
        "website": "https://www.mfg.comhttps://www.mfg.com/manufacturer/anxin-metal-plastic-products-hk-co-limited-guangdong-1773414",
        "country": "Asia",
        "industries_served": [
            "General Manufacturing"
        ],
        "manufacturing_processes": [
            "Unknown"
        ],
        "certifications": [
            "Unknown"
        ],
        "customers": [
            "Unknown"
        ],
        "employees": "Unknown",
        "annual_revenue": "Unknown",
        "score": 1
    },
    {
        "company_name": "Nanjing Pusher Machinery Co.,Ltd",
        "website": "https://www.mfg.comhttps://www.mfg.com/manufacturer/nanjing-pusher-machinery-coltd-nanjing-jiangsu-1441978",
        "country": "Asia",
        "industries_served": [
            "General Manufacturing"
        ],
        "manufacturing_processes": [
            "Unknown"
        ],
        "certifications": [
            "Unknown"
        ],
        "customers": [
            "Unknown"
        ],
        "employees": "Unknown",
        "annual_revenue": "Unknown",
        "score": 1
    },
    {
        "company_name": "Ansla Science Technology Co., Limited",
        "website": "https://www.mfg.comhttps://www.mfg.com/manufacturer/ansla-science-technology-co-limited-guangdong-494545",
        "country": "Asia",
        "industries_served": [
            "General Manufacturing"
        ],
        "manufacturing_processes": [
            "Unknown"
        ],
        "certifications": [
            "Unknown"
        ],
        "customers": [
            "Unknown"
        ],
        "employees": "Unknown",
        "annual_revenue": "Unknown",
        "score": 1
    },
    {
        "company_name": "Ningbo Youlin Manufacturing Co., Ltd",
        "website": "https://www.mfg.comhttps://www.mfg.com/manufacturer/ningbo-youlin-manufacturing-co-ltd-ningbo-zhejiang-363564",
        "country": "Asia",
        "industries_served": [
            "General Manufacturing"
        ],
        "manufacturing_processes": [
            "Unknown"
        ],
        "certifications": [
            "Unknown"
        ],
        "customers": [
            "Unknown"
        ],
        "employees": "Unknown",
        "annual_revenue": "Unknown",
        "score": 1
    },
    {
        "company_name": "Sunny High Precision Machining",
        "website": "https://www.mfg.comhttps://www.mfg.com/manufacturer/sunny-high-precision-machining-guangdong-477728",
        "country": "Asia",
        "industries_served": [
            "General Manufacturing"
        ],
        "manufacturing_processes": [
            "Unknown"
        ],
        "certifications": [
            "Unknown"
        ],
        "customers": [
            "Unknown"
        ],
        "employees": "Unknown",
        "annual_revenue": "Unknown",
        "score": 1
    },
    {
        "company_name": "SHI HE PRECISION PRODUCT(SHENZHEN) CO.,LTD",
        "website": "https://www.mfg.comhttps://www.mfg.com/manufacturer/shi-he-precision-productshenzhen-coltd-shenzhen-guangdong-1844941",
        "country": "Asia",
        "industries_served": [
            "General Manufacturing"
        ],
        "manufacturing_processes": [
            "Unknown"
        ],
        "certifications": [
            "Unknown"
        ],
        "customers": [
            "Unknown"
        ],
        "employees": "Unknown",
        "annual_revenue": "Unknown",
        "score": 1
    },
    {
        "company_name": "TIANJIN ZHENHUA INDUSTRY CO.,LTD",
        "website": "https://www.mfg.comhttps://www.mfg.com/manufacturer/tianjin-zhenhua-industry-coltd-tianjin-1535301",
        "country": "Asia",
        "industries_served": [
            "General Manufacturing"
        ],
        "manufacturing_processes": [
            "Unknown"
        ],
        "certifications": [
            "Unknown"
        ],
        "customers": [
            "Unknown"
        ],
        "employees": "Unknown",
        "annual_revenue": "Unknown",
        "score": 1
    },
    {
        "company_name": "Dongguan Shi bei Xin metal products Co., LTD",
        "website": "https://www.mfg.comhttps://www.mfg.com/manufacturer/dongguan-shi-bei-xin-metal-products-co-ltd-dongguan-guangdong-1866013",
        "country": "Asia",
        "industries_served": [
            "General Manufacturing"
        ],
        "manufacturing_processes": [
            "Unknown"
        ],
        "certifications": [
            "Unknown"
        ],
        "customers": [
            "Unknown"
        ],
        "employees": "Unknown",
        "annual_revenue": "Unknown",
        "score": 1
    },
    {
        "company_name": "Nanjing Best International Co.,Ltd.",
        "website": "https://www.mfg.comhttps://www.mfg.com/manufacturer/nanjing-best-international-coltd-nanjing-jiangsu-1418730",
        "country": "Asia",
        "industries_served": [
            "General Manufacturing"
        ],
        "manufacturing_processes": [
            "Unknown"
        ],
        "certifications": [
            "Unknown"
        ],
        "customers": [
            "Unknown"
        ],
        "employees": "Unknown",
        "annual_revenue": "Unknown",
        "score": 1
    },
    {
        "company_name": "Hebei Metals & Minerals Corp. Ltd",
        "website": "https://www.mfg.comhttps://www.mfg.com/manufacturer/hebei-metals-minerals-corp-ltd-shijiazhuang-hebei-364132",
        "country": "Asia",
        "industries_served": [
            "General Manufacturing"
        ],
        "manufacturing_processes": [
            "Unknown"
        ],
        "certifications": [
            "Unknown"
        ],
        "customers": [
            "Unknown"
        ],
        "employees": "Unknown",
        "annual_revenue": "Unknown",
        "score": 1
    },
    {
        "company_name": "Kunshan Willcan Mold CO.,LTD",
        "website": "https://www.mfg.comhttps://www.mfg.com/manufacturer/kunshan-willcan-mold-coltd-jiangsu-1874541",
        "country": "Asia",
        "industries_served": [
            "General Manufacturing"
        ],
        "manufacturing_processes": [
            "Unknown"
        ],
        "certifications": [
            "Unknown"
        ],
        "customers": [
            "Unknown"
        ],
        "employees": "Unknown",
        "annual_revenue": "Unknown",
        "score": 1
    },
    {
        "company_name": "Wuxi Baide Precision CNC machining Machinery",
        "website": "https://www.mfg.comhttps://www.mfg.com/manufacturer/wuxi-baide-precision-cnc-machining-machinery-wuxi-jiangsu-1495819",
        "country": "Asia",
        "industries_served": [
            "General Manufacturing"
        ],
        "manufacturing_processes": [
            "Unknown"
        ],
        "certifications": [
            "Unknown"
        ],
        "customers": [
            "Unknown"
        ],
        "employees": "Unknown",
        "annual_revenue": "Unknown",
        "score": 1
    },
    {
        "company_name": "HuangYu Precision Metal Products Co.,Limited",
        "website": "https://www.mfg.comhttps://www.mfg.com/manufacturer/huangyu-precision-metal-products-colimited-dongguan-guangdong-1772773",
        "country": "Asia",
        "industries_served": [
            "General Manufacturing"
        ],
        "manufacturing_processes": [
            "Unknown"
        ],
        "certifications": [
            "Unknown"
        ],
        "customers": [
            "Unknown"
        ],
        "employees": "Unknown",
        "annual_revenue": "Unknown",
        "score": 1
    },
    {
        "company_name": "FY Parts llc",
        "website": "https://www.mfg.comhttps://www.mfg.com/manufacturer/fy-parts-llc-jiangsu-1446791",
        "country": "Asia",
        "industries_served": [
            "General Manufacturing"
        ],
        "manufacturing_processes": [
            "Unknown"
        ],
        "certifications": [
            "Unknown"
        ],
        "customers": [
            "Unknown"
        ],
        "employees": "Unknown",
        "annual_revenue": "Unknown",
        "score": 1
    },
    {
        "company_name": "Diode Machining Technology China Limited",
        "website": "https://www.mfg.comhttps://www.mfg.com/manufacturer/diode-machining-technology-china-limited-guangzhou-guangdong-1769225",
        "country": "Asia",
        "industries_served": [
            "General Manufacturing"
        ],
        "manufacturing_processes": [
            "Unknown"
        ],
        "certifications": [
            "Unknown"
        ],
        "customers": [
            "Unknown"
        ],
        "employees": "Unknown",
        "annual_revenue": "Unknown",
        "score": 1
    },
    {
        "company_name": "LI DE METAL PLASTIC CO., LIMITED",
        "website": "https://www.mfg.comhttps://www.mfg.com/manufacturer/li-de-metal-plastic-co-limited-dongguan-city-guangdong-638589",
        "country": "Asia",
        "industries_served": [
            "General Manufacturing"
        ],
        "manufacturing_processes": [
            "Unknown"
        ],
        "certifications": [
            "Unknown"
        ],
        "customers": [
            "Unknown"
        ],
        "employees": "Unknown",
        "annual_revenue": "Unknown",
        "score": 1
    },
    {
        "company_name": "Ningbo Bojie Jingzhu Machine Co.,Ltd.",
        "website": "https://www.mfg.comhttps://www.mfg.com/manufacturer/ningbo-bojie-jingzhu-machine-coltd-ningbo-zhejiang-485696",
        "country": "Asia",
        "industries_served": [
            "General Manufacturing"
        ],
        "manufacturing_processes": [
            "Unknown"
        ],
        "certifications": [
            "Unknown"
        ],
        "customers": [
            "Unknown"
        ],
        "employees": "Unknown",
        "annual_revenue": "Unknown",
        "score": 1
    },
    {
        "company_name": "Mulmic Co.,LTD",
        "website": "https://www.mfg.comhttps://www.mfg.com/manufacturer/mulmic-coltd-guangdong-1858566",
        "country": "Asia",
        "industries_served": [
            "General Manufacturing"
        ],
        "manufacturing_processes": [
            "Unknown"
        ],
        "certifications": [
            "Unknown"
        ],
        "customers": [
            "Unknown"
        ],
        "employees": "Unknown",
        "annual_revenue": "Unknown",
        "score": 1
    },
    {
        "company_name": "Ningbo SV Plastic Hardware Co., Ltd",
        "website": "https://www.mfg.comhttps://www.mfg.com/manufacturer/ningbo-sv-plastic-hardware-co-ltd-huangyan-city-zhejiang-1191645",
        "country": "Asia",
        "industries_served": [
            "General Manufacturing"
        ],
        "manufacturing_processes": [
            "Unknown"
        ],
        "certifications": [
            "Unknown"
        ],
        "customers": [
            "Unknown"
        ],
        "employees": "Unknown",
        "annual_revenue": "Unknown",
        "score": 1
    },
    {
        "company_name": "Shanxi Fuding International Trade Co., Ltd.",
        "website": "https://www.mfg.comhttps://www.mfg.com/manufacturer/shanxi-fuding-international-trade-co-ltd-taiyuan-shanxi-1767801",
        "country": "Asia",
        "industries_served": [
            "General Manufacturing"
        ],
        "manufacturing_processes": [
            "Unknown"
        ],
        "certifications": [
            "Unknown"
        ],
        "customers": [
            "Unknown"
        ],
        "employees": "Unknown",
        "annual_revenue": "Unknown",
        "score": 1
    }
]